{
  "English": {
    "welcome": "Welcome to Vocabulary Builder!",
    "welcome_subheader": "Here you can add new words, learn them and see your progress.",
    "sign_up": "Sign up",
    "sign_up_message": "To create an account",
    "log_in": "Log in",
    "log_in_message": "To log into an existing account",
    "instructions": "Instrucitions",
    "instructions_message": "To see how the app works",
    "name_": "Name",
    "email_": "Email",
    "password_": "Password",
    "create_user": "Create User",
    "continue_": "Continue",
    "already_have_an_aссount": "Already have an account?",
    "dont_have_an_aссount": "Don't have an account?",
    "empty_fields_err": "All fields should be filled",
    "wrong_credentials_err": "Wrong credentials",
    "account_exists_err": "Account already exists",
    "email_invalid_err": "Email is invalid",
    "password_invalid_err": "Password should be 6 charecters minimum",
    "enter_a_word": "Enter a word",
    "search": "Search",
    "start_entering_a_word": "Start entering a word",
    "show_all": "Show All",

    "HomePage": {
      "nice_to_see_you": "Nice to see you here!",
      "what_would_you_like_to_do": "What would you like to do?",
      "vocabulary_explanation": "To add and browse words",
      "progress_explanation": "To see your learning progress",
      "learn_explanation": "To learn vocabulary"
    },

    "ProgressPage": {
      "progress": "PROGRESS",
      "here_you_can_see_your_progress": "Here you can see your progress.",
      "add_vocabulary_message": "Please, add some vocabulary first.",
      "go_to_vocabulary": "GO TO VOCABULARY"
    },

    "VocabularyPage": {
      "add_vocabulary": "ADD VOCABULARY",
      "add": "ADD",
      "here_will_be_your_words": "Here will be your words."
    },

    "ExplanatoryWordsCard": {
      "new_type_explanation": "added but not reviewed yet",
      "learning_type_explanation": "reviewed but not learned",
      "learned_type_explanation": "learned well"
    },

    "Preferences": {
      "preferences": "PREFERENCES",
      "how_many_words_to_review": "How many words would you like to review?",
      "you_have_in_total_in_total": "You have in total",
      "words": "word(s)",
      "show_word_types": "Show word types",
      "close_word_types": "Close word types",
      "fill_the_preferences": "Please, fill in the preferences in numbers and press START.",
      "start": "START",
      "new_form_label": "New words",
      "learning_form_label": "Learning words",
      "learned_form_label": "Learned words",

      "errors": {
        "enter_numbers": "Please, enter NUMBERS",
        "the_number_should_be_positive_and": "the number should be positive and",
        "_maximum": "maximum",
        "add_vocabulary_before_learning": "Please, add some vocabulary before learning"
      }
    },

    "shared": {
      "vocabulary": "Vocabulary",
      "progress": "Progress",
      "learn": "Learn",
      "new_type": "New",
      "learning_type": "Learning",
      "learned_type": "Learned",
      "words": "Words",
      "foreign_word": "Foreign word",
      "translation_word": "Translation"
    }
  },
  "Russian": {
    "welcome": "Добро пожаловать в Vocabulary Builder!",
    "welcome_subheader": "Здесь вы можете добавлять новые слова, учить их и отслеживать прогресс.",
    "sign_up": "Регистрация",
    "sign_up_message": "Cоздать аккаунт",
    "log_in": "Bxoд",
    "log_in_message": "Войти в аккаунт",
    "instructions": "Инструкции",
    "instructions_message": "Как работает приложение?",
    "name_": "Имя",
    "email_": "Электронная почта",
    "password_": "Пароль",
    "create_user": "Создать Аккаунт",
    "continue_": "Продолжить",
    "already_have_an_aссount": "Уже есть аккаунт?",
    "dont_have_an_aссount": "Ещё нет аккаунта?",
    "empty_fields_err": "Все поля должны быть заполнены",
    "wrong_credentials_err": "Аккаунт не найден",
    "account_exists_err": "Аккаунт уже существует",
    "email_invalid_err": "Email недействителен",
    "password_invalid_err": "Пароль должен быть не менее 6 символов",
    "enter_a_word": "Введите слово",
    "search": "Поиск",
    "start_entering_a_word": "Начните вводить слово",
    "show_all": "Показать все",

    "HomePage": {
      "nice_to_see_you": "Добро пожаловать!",
      "what_would_you_like_to_do": "Что бы вы хотели сделать?",
      "vocabulary_explanation": "Добавлять и искать слова",
      "progress_explanation": "Посмотреть прогресс",
      "learn_explanation": "Учить слова"
    },

    "ProgressPage": {
      "progress": "ПРОГРЕСС",
      "here_you_can_see_your_progress": "Здесь вы можете отслеживать ваш прогресс.",
      "add_vocabulary_message": "Пожалуйста, сначала добавьте слова",
      "go_to_vocabulary": "ДОБАВИТЬ СЛОВА"
    },

    "ExplanatoryWordsCard": {
      "new_type_explanation": "добавленные, но ещё не просмотренные",
      "learning_type_explanation": "просмотренные, но ещё не выученные",
      "learned_type_explanation": "выученные хорошо"
    },

    "VocabularyPage": {
      "add_vocabulary": "ДОБАВИТЬ СЛОВА",
      "add": "ДОБАВИТЬ",
      "here_will_be_your_words": "Здесь будут ваши слова."
    },

    "PreferencesPage": {
      "preferences": "ПРЕДПОЧТЕНИЯ",
      "how_many_words_to_review": "Сколько слов вы бы хотели просмотреть?",
      "you_have_in_total": "У вас есть всего",
      "words": "слов(о)",
      "_in_total": "в сумме",
      "show_word_types": "Показать типы слов",
      "close_word_types": "Скрыть типы слов",
      "fill_the_preferences": "Пожалуйста, заполните предпочтения в числах и нажмите НАЧАТЬ.",
      "start": "НАЧАТЬ",
      "new_form_label": "Новые слова",
      "learning_form_label": "Слова в процессе",
      "learned_form_label": "Выученные слова",

      "errors": {
        "enter_numbers": "Пожалуйста, введите ЧИСЛА",
        "the_number_should_be_positive_and": "число должно быть положительным и",
        "_maximum": "максимум",
        "add_vocabulary_before_learning": "Пожалуйста, сначала добавьте слова"
      }
    },

    "shared": {
      "vocabulary": "Мои слова",
      "progress": "Прогресс",
      "learn": "Изучение",
      "empty_fields_err": "Все поля должны быть заполнены",
      "new_type": "Новые",
      "learning_type": "В процессе",
      "learned_type": "Выученные",
      "words": "Слова",
      "foreign_word": "Иностранно слово",
      "translation_word": "Перевод"
    }
  }
}
